{
  "created_utc": "2026-03-24T15:04:25.884143+00:00",
  "train_image": "img/Essex_Faces/94/asamma.19.jpg",
  "test_image": "img/Essex_Faces/94/asamma.19.jpg",
  "features": "cbcr_grad",
  "feature_names": [
    "Cb",
    "Cr",
    "|grad(Y)|"
  ],
  "k": 6,
  "skin_clusters": [
    2,
    3
  ],
  "train_image_shape": [
    200,
    180,
    3
  ],
  "test_image_shape": [
    200,
    180,
    3
  ],
  "cluster_centers_file": "centers.json",
  "normalization": {
    "type": "zscore_from_train_image",
    "mean": [
      118.59322357177734,
      127.57780456542969,
      55.59078598022461
    ],
    "std": [
      16.471813201904297,
      12.359359741210938,
      74.70217895507812
    ]
  }
}